sshadder/__init__.py
sshadder/cli.py
sshadder/sshadder.py
sshadder-0.3.1.dist-info/DESCRIPTION.rst
sshadder-0.3.1.dist-info/METADATA
sshadder-0.3.1.dist-info/RECORD
sshadder-0.3.1.dist-info/WHEEL
sshadder-0.3.1.dist-info/entry_points.txt
sshadder-0.3.1.dist-info/metadata.json
sshadder-0.3.1.dist-info/pbr.json
sshadder-0.3.1.dist-info/top_level.txt
