Metadata-Version: 2.0
Name: sshadder
Version: 0.3.1
Summary: Automatic loader of ssh keys
Home-page: https://github.com/mvk/sshadder
Author: Max Kovgan
Author-email: maxk@devopsent.biz
License: Apache-2
Keywords: setup
Requires-Dist: pycrypto (==2.6.1)
Requires-Dist: simple-crypt (==4.1.7)
Requires-Dist: pexpect (==4.2.1)
